a1/__init__.py
a1/builtin_tools.py
a1/cfg_builder.py
a1/cli.py
a1/code_utils.py
a1/codecheck.py
a1/codecost.py
a1/codefix.py
a1/codegen.py
a1/context.py
a1/em.py
a1/executor.py
a1/extra_codecheck.py
a1/extra_strategies.py
a1/llm.py
a1/models.py
a1/rag.py
a1/rag_router.py
a1/runtime.py
a1/schema_utils.py
a1/serialization.py
a1/strategies.py
a1_compiler-0.1.6.dist-info/METADATA
a1_compiler-0.1.6.dist-info/WHEEL
a1_compiler-0.1.6.dist-info/entry_points.txt
a1_compiler-0.1.6.dist-info/licenses/LICENSE
a1_compiler-0.1.6.dist-info/RECORD
