Metadata-Version: 2.4
Name: a1-compiler
Version: 0.1.6
Summary: An optimizing agent-to-code compiler
Author-email: Caleb Winston <calebhwin@gmail.com>
License-File: LICENSE
Keywords: agents,ai,code-generation,compiler,llm
Classifier: Development Status :: 3 - Alpha
Classifier: Intended Audience :: Developers
Classifier: License :: OSI Approved :: Apache Software License
Classifier: Programming Language :: Python :: 3.12
Classifier: Programming Language :: Python :: 3.13
Requires-Python: >=3.12
Requires-Dist: any-llm-sdk[all]>=1.0.0
Requires-Dist: fsspec>=2024.0.0
Requires-Dist: httpx>=0.27.0
Requires-Dist: mcp-use>=0.1.0
Requires-Dist: opentelemetry-api>=1.20.0
Requires-Dist: opentelemetry-sdk>=1.20.0
Requires-Dist: pydantic>=2.10.0
Requires-Dist: python-dotenv>=1.0.0
Requires-Dist: pyyaml>=6.0.0
Requires-Dist: sqlalchemy>=2.0.0
Provides-Extra: dev
Requires-Dist: fastapi>=0.115.0; extra == 'dev'
Requires-Dist: mypy>=1.13.0; extra == 'dev'
Requires-Dist: pytest-asyncio>=0.24.0; extra == 'dev'
Requires-Dist: pytest-cov>=6.0.0; extra == 'dev'
Requires-Dist: pytest>=8.0.0; extra == 'dev'
Requires-Dist: ruff>=0.8.0; extra == 'dev'
Requires-Dist: uvicorn>=0.30.0; extra == 'dev'
Provides-Extra: examples
Requires-Dist: z3-solver>=4.13.0; extra == 'examples'
